duoyinfixer/__init__.py
duoyinfixer/duoyinfixer.py
duoyinfixer-0.1.dist-info/METADATA
duoyinfixer-0.1.dist-info/WHEEL
duoyinfixer-0.1.dist-info/top_level.txt
duoyinfixer-0.1.dist-info/RECORD
