Metadata-Version: 2.1
Name: duoyinfixer
Version: 0.1
Summary: =?utf-8?b?5pu/5o2i5Y+l5a2Q5Lit55qE5aSa6Z+z5a2X77yM6Ziy5q2i5paH5a2X6YWN6Z+z5Lit5Zug5Li65aSa6Z+z5a2X6ICM5Ye6546w6Zeu6aKY?=
Author: LY
Requires-Dist: pypinyin
